{"name":"信息社会","slug":"信息社会","count":1,"postlist":[{"title":"信息工厂","slug":"design/info-factory","date":"2010-03-07T03:04:31.000Z","updated":"2018-04-11T08:14:41.496Z","comments":true,"path":"api/articles/design/info-factory.json","excerpt":"","keywords":null,"cover":null,"content":"<p>信息技术研发<br>自助下载机（同ATM）<br>特点：USB连接，自定义下载，电子拷贝收费系统<br>信息综合理论：将不同信息综合到同一环境下，形成爆炸效应。<br>信息化理论：所有实物都能转化为信息，包括图书，音像，操作程序，乃至整个社会。</p>\n<p>信息工厂发展规划<br>第一阶段 图书、下载与资讯<br>第二阶段 增加服务：多媒体设备培训与辅导（耳塞静音，透明隔层），电影工作室<br>第三阶段 软件支持：互动信息平台，信息咨询，网络购物中介<br>第四阶段 建成自动化信息处理站（信息银行），深化资源信息化通道，信息污染预防体系<br>第五阶段 设立信息技术研究部<br>公益计划<br>编写成人文化学习的教材，并定期培训（需调查取证），就业培训<br>信息社区整合信息图书馆、电影院、舞台、教室、休闲学习茶厅、信息商务等为社会建设第二课堂，建起社区农村与城市沟通的桥梁<br>为每个社区或村舍建立信息工厂，以及与其相连的信息商务平台（新型商店，创意产品展台租赁商店，旧货信息登记），以形成一体化产业，为国家增加就业。</p>\n<p>目前信息工厂可分为：临时研发总部，资源库及共享计划中心，信息生产部（制造信息并向大众传授信息生产的技术），信息展台（输出端口，便民社区性质），信息商务（电子商务）。<br>信息工厂是各种信息交流的中心，是新技术新创意产生商业效应的研究中心，是高端文化向低端文化流动的江河，是信息一体化带动社会进步的金融中心（信息银行或助动机）。</p>\n<p>信息工厂的主要经营方向<br>一是国家扶持，使其成为带有公共性质的国有产业<br>二是信息服务收费，为商家提供专业的信息服务<br>三是文化产业，经营图书（阅览室）、静音（耳塞，口形识别，音乐）电影茶厅<br>四是技术产业，信息制作与下载服务，教育与技术培训（包括教授制作和运用信息的技术），城市就业与自主创业指导<br>五是信息商务，包括网店中介型信息商店，创意产品展台租赁商店，旧货信息自助交易平台<br>六是信息发布，公益性广告，便民信息发布<br>七是制作信息文凭与信息档案<br>六是研发应用</p>\n","text":"信息技术研发<br>自助下载机（同ATM）<br>特点：USB连接，自定义下载，电子拷贝收费系统<br>信息综合理论：将不同信息综合到同一环境下，形成爆炸效应。<br>信息化理论：所有实物都能转化为信息，包括图书，音像，操作程序，乃至整个社会。信息工厂发展规划<br>第一阶段 图","link":"","raw":null,"photos":[],"categories":[{"name":"设计","slug":"设计","count":10,"path":"api/categories/设计.json"}],"tags":[{"name":"信息社会","slug":"信息社会","count":1,"path":"api/tags/信息社会.json"}]}]}